leetcode_project_generator-1.6.0.dist-info/licenses/LICENSE
lpg/__init__.py
lpg/__main__.py
lpg/constants.py
lpg/lpg.py
lpg/interfaces/__init__.py
lpg/interfaces/file.py
lpg/interfaces/lang_test.py
lpg/interfaces/web.py
lpg/interfaces/lang/__init__.py
lpg/interfaces/lang/base.py
lpg/interfaces/lang/c.py
lpg/interfaces/lang/golang.py
lpg/interfaces/lang/java.py
lpg/interfaces/lang/javascript.py
lpg/interfaces/lang/python.py
lpg/interfaces/lang/python3.py
lpg/interfaces/lang/typescript.py
leetcode_project_generator-1.6.0.dist-info/METADATA
leetcode_project_generator-1.6.0.dist-info/WHEEL
leetcode_project_generator-1.6.0.dist-info/entry_points.txt
leetcode_project_generator-1.6.0.dist-info/top_level.txt
leetcode_project_generator-1.6.0.dist-info/RECORD
