Metadata-Version: 2.4
Name: leetcode-project-generator
Version: 1.6.0
Summary: A LeetCode project template generator.
Author-email: Konrad Guzek <konrad@guzek.uk>
Project-URL: Homepage, https://github.com/kguzek/leetcode-project-generator#readme
Project-URL: Issues, https://github.com/kguzek/leetcode-project-generator/issues
Classifier: Programming Language :: Python :: 3
Classifier: License :: OSI Approved :: MIT License
Classifier: Operating System :: OS Independent
Requires-Python: >=3.10
License-File: LICENSE
Requires-Dist: click
Dynamic: license-file
